PyCpep/__init__.py
PyCpep/pycpep.py
PyCpep/mdl/model.h5
PyCpep/mdl/model.hdf5
PyCpep/mdl/scaler.pkl
pycpep-1.1.1.dist-info/LICENSE.txt
pycpep-1.1.1.dist-info/METADATA
pycpep-1.1.1.dist-info/WHEEL
pycpep-1.1.1.dist-info/top_level.txt
pycpep-1.1.1.dist-info/RECORD
