Metadata-Version: 2.1
Name: pycpep
Version: 1.1.1
Summary: Predicts deviation in the heat capacity measurement for microDSC Tian-Calvet
Home-page: https://github.com/nirmalparmarphd/PyCpep
Author: Nirmal Parmar
Author-email: nirmalparmarphd@gmail.com
License: MIT
License-File: LICENSE.txt
Requires-Dist: scikit-learn
Requires-Dist: numpy
Requires-Dist: h5py
Requires-Dist: keras
Requires-Dist: gitpython
Requires-Dist: pandas
